{
  "0.0": [
    {
      "channel": 0.0,
      "note": 64.0,
      "time": 0,
      "type": "note_on",
      "velocity": 72.0,
      "note_midi_value": 64.0,
      "note_velocity": 72.0,
      "note_time": 0,
      "note_seconds": 0.0,
      "tpb": 220,
      "channel_chunk": "0.0_0.0",
      "instrument": "Acoustic Guitar (nylon)",
      "octave": 5.0,
      "note_value": 4.0,
      "note_value_nmd": 4,
      "note_name": "E",
      "angle": 120
    },
    {
      "channel": 0.0,
      "note": 55.0,
      "time": 0,
      "type": "note_on",
      "velocity": 70.0,
      "note_midi_value": 55.0,
      "note_velocity": 70.0,
      "note_time": 0,
      "note_seconds": 0.0,
      "tpb": 220,
      "channel_chunk": "0.0_0.0",
      "instrument": "Acoustic Guitar (nylon)",
      "octave": 4.0,
      "note_value": 7.0,
      "note_value_nmd": 1,
      "note_name": "C#",
      "angle": 210
    },
    {
      "channel": 0.0,
      "note": 62.0,
      "time": 25,
      "type": "note_on",
      "velocity": 72.0,
      "note_midi_value": 62.0,
      "note_velocity": 72.0,
      "note_time": 256,
      "note_seconds": 0.5818181818181818,
      "tpb": 220,
      "channel_chunk": "0.0_0.0",
      "instrument": "Acoustic Guitar (nylon)",
      "octave": 5.0,
      "note_value": 2.0,
      "note_value_nmd": 2,
      "note_name": "D",
      "angle": 60
    },
    {
      "channel": 0.0,
      "note": 60.0,
      "time": 25,
      "type": "note_on",
      "velocity": 71.0,
      "note_midi_value": 60.0,
      "note_velocity": 71.0,
      "note_time": 512,
      "note_seconds": 1.1636363636363636,
      "tpb": 220,
      "channel_chunk": "0.0_0.0",
      "instrument": "Acoustic Guitar (nylon)",
      "octave": 5.0,
      "note_value": 0.0,
      "note_value_nmd": 0,
      "note_name": "C",
      "angle": 0
    },
    {
      "channel": 0.0,
      "note": 62.0,
      "time": 25,
      "type": "note_on",
      "velocity": 79.0,
      "note_midi_value": 62.0,
      "note_velocity": 79.0,
      "note_time": 768,
      "note_seconds": 1.7454545454545454,
      "tpb": 220,
      "channel_chunk": "0.0_0.0",
      "instrument": "Acoustic Guitar (nylon)",
      "octave": 5.0,
      "note_value": 2.0,
      "note_value_nmd": 2,
      "note_name": "D",
      "angle": 60
    },
    {
      "channel": 0.0,
      "note": 64.0,
      "time": 25,
      "type": "note_on",
      "velocity": 85.0,
      "note_midi_value": 64.0,
      "note_velocity": 85.0,
      "note_time": 1024,
      "note_seconds": 2.327272727272727,
      "tpb": 220,
      "channel_chunk": "0.0_0.0",
      "instrument": "Acoustic Guitar (nylon)",
      "octave": 5.0,
      "note_value": 4.0,
      "note_value_nmd": 4,
      "note_name": "E",
      "angle": 120
    },
    {
      "channel": 0.0,
      "note": 55.0,
      "time": 0,
      "type": "note_on",
      "velocity": 79.0,
      "note_midi_value": 55.0,
      "note_velocity": 79.0,
      "note_time": 1024,
      "note_seconds": 2.327272727272727,
      "tpb": 220,
      "channel_chunk": "0.0_0.0",
      "instrument": "Acoustic Guitar (nylon)",
      "octave": 4.0,
      "note_value": 7.0,
      "note_value_nmd": 1,
      "note_name": "C#",
      "angle": 210
    },
    {
      "channel": 0.0,
      "note": 64.0,
      "time": 25,
      "type": "note_on",
      "velocity": 78.0,
      "note_midi_value": 64.0,
      "note_velocity": 78.0,
      "note_time": 1280,
      "note_seconds": 2.909090909090909,
      "tpb": 220,
      "channel_chunk": "0.0_0.0",
      "instrument": "Acoustic Guitar (nylon)",
      "octave": 5.0,
      "note_value": 4.0,
      "note_value_nmd": 4,
      "note_name": "E",
      "angle": 120
    },
    {
      "channel": 0.0,
      "note": 64.0,
      "time": 25,
      "type": "note_on",
      "velocity": 74.0,
      "note_midi_value": 64.0,
      "note_velocity": 74.0,
      "note_time": 1536,
      "note_seconds": 3.4909090909090907,
      "tpb": 220,
      "channel_chunk": "0.0_0.0",
      "instrument": "Acoustic Guitar (nylon)",
      "octave": 5.0,
      "note_value": 4.0,
      "note_value_nmd": 4,
      "note_name": "E",
      "angle": 120
    },
    {
      "channel": 0.0,
      "note": 62.0,
      "time": 50,
      "type": "note_on",
      "velocity": 75.0,
      "note_midi_value": 62.0,
      "note_velocity": 75.0,
      "note_time": 2048,
      "note_seconds": 4.654545454545454,
      "tpb": 220,
      "channel_chunk": "0.0_1.0",
      "instrument": "Acoustic Guitar (nylon)",
      "octave": 5.0,
      "note_value": 2.0,
      "note_value_nmd": 2,
      "note_name": "D",
      "angle": 60
    },
    {
      "channel": 0.0,
      "note": 55.0,
      "time": 0,
      "type": "note_on",
      "velocity": 77.0,
      "note_midi_value": 55.0,
      "note_velocity": 77.0,
      "note_time": 2048,
      "note_seconds": 4.654545454545454,
      "tpb": 220,
      "channel_chunk": "0.0_1.0",
      "instrument": "Acoustic Guitar (nylon)",
      "octave": 4.0,
      "note_value": 7.0,
      "note_value_nmd": 1,
      "note_name": "C#",
      "angle": 210
    },
    {
      "channel": 0.0,
      "note": 62.0,
      "time": 25,
      "type": "note_on",
      "velocity": 77.0,
      "note_midi_value": 62.0,
      "note_velocity": 77.0,
      "note_time": 2304,
      "note_seconds": 5.236363636363636,
      "tpb": 220,
      "channel_chunk": "0.0_1.0",
      "instrument": "Acoustic Guitar (nylon)",
      "octave": 5.0,
      "note_value": 2.0,
      "note_value_nmd": 2,
      "note_name": "D",
      "angle": 60
    },
    {
      "channel": 0.0,
      "note": 62.0,
      "time": 25,
      "type": "note_on",
      "velocity": 75.0,
      "note_midi_value": 62.0,
      "note_velocity": 75.0,
      "note_time": 2560,
      "note_seconds": 5.818181818181818,
      "tpb": 220,
      "channel_chunk": "0.0_1.0",
      "instrument": "Acoustic Guitar (nylon)",
      "octave": 5.0,
      "note_value": 2.0,
      "note_value_nmd": 2,
      "note_name": "D",
      "angle": 60
    },
    {
      "channel": 0.0,
      "note": 64.0,
      "time": 50,
      "type": "note_on",
      "velocity": 82.0,
      "note_midi_value": 64.0,
      "note_velocity": 82.0,
      "note_time": 3072,
      "note_seconds": 6.9818181818181815,
      "tpb": 220,
      "channel_chunk": "0.0_1.0",
      "instrument": "Acoustic Guitar (nylon)",
      "octave": 5.0,
      "note_value": 4.0,
      "note_value_nmd": 4,
      "note_name": "E",
      "angle": 120
    },
    {
      "channel": 0.0,
      "note": 55.0,
      "time": 0,
      "type": "note_on",
      "velocity": 79.0,
      "note_midi_value": 55.0,
      "note_velocity": 79.0,
      "note_time": 3072,
      "note_seconds": 6.9818181818181815,
      "tpb": 220,
      "channel_chunk": "0.0_1.0",
      "instrument": "Acoustic Guitar (nylon)",
      "octave": 4.0,
      "note_value": 7.0,
      "note_value_nmd": 1,
      "note_name": "C#",
      "angle": 210
    },
    {
      "channel": 0.0,
      "note": 67.0,
      "time": 25,
      "type": "note_on",
      "velocity": 84.0,
      "note_midi_value": 67.0,
      "note_velocity": 84.0,
      "note_time": 3328,
      "note_seconds": 7.5636363636363635,
      "tpb": 220,
      "channel_chunk": "0.0_1.0",
      "instrument": "Acoustic Guitar (nylon)",
      "octave": 5.0,
      "note_value": 7.0,
      "note_value_nmd": 1,
      "note_name": "C#",
      "angle": 210
    },
    {
      "channel": 0.0,
      "note": 67.0,
      "time": 25,
      "type": "note_on",
      "velocity": 75.0,
      "note_midi_value": 67.0,
      "note_velocity": 75.0,
      "note_time": 3584,
      "note_seconds": 8.145454545454545,
      "tpb": 220,
      "channel_chunk": "0.0_2.0",
      "instrument": "Acoustic Guitar (nylon)",
      "octave": 5.0,
      "note_value": 7.0,
      "note_value_nmd": 1,
      "note_name": "C#",
      "angle": 210
    },
    {
      "channel": 0.0,
      "note": 64.0,
      "time": 50,
      "type": "note_on",
      "velocity": 73.0,
      "note_midi_value": 64.0,
      "note_velocity": 73.0,
      "note_time": 4096,
      "note_seconds": 9.309090909090909,
      "tpb": 220,
      "channel_chunk": "0.0_2.0",
      "instrument": "Acoustic Guitar (nylon)",
      "octave": 5.0,
      "note_value": 4.0,
      "note_value_nmd": 4,
      "note_name": "E",
      "angle": 120
    },
    {
      "channel": 0.0,
      "note": 55.0,
      "time": 0,
      "type": "note_on",
      "velocity": 78.0,
      "note_midi_value": 55.0,
      "note_velocity": 78.0,
      "note_time": 4096,
      "note_seconds": 9.309090909090909,
      "tpb": 220,
      "channel_chunk": "0.0_2.0",
      "instrument": "Acoustic Guitar (nylon)",
      "octave": 4.0,
      "note_value": 7.0,
      "note_value_nmd": 1,
      "note_name": "C#",
      "angle": 210
    },
    {
      "channel": 0.0,
      "note": 62.0,
      "time": 25,
      "type": "note_on",
      "velocity": 69.0,
      "note_midi_value": 62.0,
      "note_velocity": 69.0,
      "note_time": 4352,
      "note_seconds": 9.89090909090909,
      "tpb": 220,
      "channel_chunk": "0.0_2.0",
      "instrument": "Acoustic Guitar (nylon)",
      "octave": 5.0,
      "note_value": 2.0,
      "note_value_nmd": 2,
      "note_name": "D",
      "angle": 60
    },
    {
      "channel": 0.0,
      "note": 60.0,
      "time": 25,
      "type": "note_on",
      "velocity": 71.0,
      "note_midi_value": 60.0,
      "note_velocity": 71.0,
      "note_time": 4608,
      "note_seconds": 10.472727272727273,
      "tpb": 220,
      "channel_chunk": "0.0_2.0",
      "instrument": "Acoustic Guitar (nylon)",
      "octave": 5.0,
      "note_value": 0.0,
      "note_value_nmd": 0,
      "note_name": "C",
      "angle": 0
    },
    {
      "channel": 0.0,
      "note": 62.0,
      "time": 25,
      "type": "note_on",
      "velocity": 80.0,
      "note_midi_value": 62.0,
      "note_velocity": 80.0,
      "note_time": 4864,
      "note_seconds": 11.054545454545455,
      "tpb": 220,
      "channel_chunk": "0.0_2.0",
      "instrument": "Acoustic Guitar (nylon)",
      "octave": 5.0,
      "note_value": 2.0,
      "note_value_nmd": 2,
      "note_name": "D",
      "angle": 60
    },
    {
      "channel": 0.0,
      "note": 64.0,
      "time": 25,
      "type": "note_on",
      "velocity": 84.0,
      "note_midi_value": 64.0,
      "note_velocity": 84.0,
      "note_time": 5120,
      "note_seconds": 11.636363636363637,
      "tpb": 220,
      "channel_chunk": "0.0_2.0",
      "instrument": "Acoustic Guitar (nylon)",
      "octave": 5.0,
      "note_value": 4.0,
      "note_value_nmd": 4,
      "note_name": "E",
      "angle": 120
    },
    {
      "channel": 0.0,
      "note": 55.0,
      "time": 0,
      "type": "note_on",
      "velocity": 79.0,
      "note_midi_value": 55.0,
      "note_velocity": 79.0,
      "note_time": 5120,
      "note_seconds": 11.636363636363637,
      "tpb": 220,
      "channel_chunk": "0.0_2.0",
      "instrument": "Acoustic Guitar (nylon)",
      "octave": 4.0,
      "note_value": 7.0,
      "note_value_nmd": 1,
      "note_name": "C#",
      "angle": 210
    },
    {
      "channel": 0.0,
      "note": 64.0,
      "time": 25,
      "type": "note_on",
      "velocity": 76.0,
      "note_midi_value": 64.0,
      "note_velocity": 76.0,
      "note_time": 5376,
      "note_seconds": 12.218181818181817,
      "tpb": 220,
      "channel_chunk": "0.0_3.0",
      "instrument": "Acoustic Guitar (nylon)",
      "octave": 5.0,
      "note_value": 4.0,
      "note_value_nmd": 4,
      "note_name": "E",
      "angle": 120
    },
    {
      "channel": 0.0,
      "note": 64.0,
      "time": 25,
      "type": "note_on",
      "velocity": 74.0,
      "note_midi_value": 64.0,
      "note_velocity": 74.0,
      "note_time": 5632,
      "note_seconds": 12.799999999999999,
      "tpb": 220,
      "channel_chunk": "0.0_3.0",
      "instrument": "Acoustic Guitar (nylon)",
      "octave": 5.0,
      "note_value": 4.0,
      "note_value_nmd": 4,
      "note_name": "E",
      "angle": 120
    },
    {
      "channel": 0.0,
      "note": 64.0,
      "time": 25,
      "type": "note_on",
      "velocity": 77.0,
      "note_midi_value": 64.0,
      "note_velocity": 77.0,
      "note_time": 5888,
      "note_seconds": 13.381818181818181,
      "tpb": 220,
      "channel_chunk": "0.0_3.0",
      "instrument": "Acoustic Guitar (nylon)",
      "octave": 5.0,
      "note_value": 4.0,
      "note_value_nmd": 4,
      "note_name": "E",
      "angle": 120
    },
    {
      "channel": 0.0,
      "note": 62.0,
      "time": 25,
      "type": "note_on",
      "velocity": 75.0,
      "note_midi_value": 62.0,
      "note_velocity": 75.0,
      "note_time": 6144,
      "note_seconds": 13.963636363636363,
      "tpb": 220,
      "channel_chunk": "0.0_3.0",
      "instrument": "Acoustic Guitar (nylon)",
      "octave": 5.0,
      "note_value": 2.0,
      "note_value_nmd": 2,
      "note_name": "D",
      "angle": 60
    },
    {
      "channel": 0.0,
      "note": 55.0,
      "time": 0,
      "type": "note_on",
      "velocity": 78.0,
      "note_midi_value": 55.0,
      "note_velocity": 78.0,
      "note_time": 6144,
      "note_seconds": 13.963636363636363,
      "tpb": 220,
      "channel_chunk": "0.0_3.0",
      "instrument": "Acoustic Guitar (nylon)",
      "octave": 4.0,
      "note_value": 7.0,
      "note_value_nmd": 1,
      "note_name": "C#",
      "angle": 210
    },
    {
      "channel": 0.0,
      "note": 62.0,
      "time": 25,
      "type": "note_on",
      "velocity": 74.0,
      "note_midi_value": 62.0,
      "note_velocity": 74.0,
      "note_time": 6400,
      "note_seconds": 14.545454545454545,
      "tpb": 220,
      "channel_chunk": "0.0_3.0",
      "instrument": "Acoustic Guitar (nylon)",
      "octave": 5.0,
      "note_value": 2.0,
      "note_value_nmd": 2,
      "note_name": "D",
      "angle": 60
    },
    {
      "channel": 0.0,
      "note": 64.0,
      "time": 25,
      "type": "note_on",
      "velocity": 81.0,
      "note_midi_value": 64.0,
      "note_velocity": 81.0,
      "note_time": 6656,
      "note_seconds": 15.127272727272727,
      "tpb": 220,
      "channel_chunk": "0.0_3.0",
      "instrument": "Acoustic Guitar (nylon)",
      "octave": 5.0,
      "note_value": 4.0,
      "note_value_nmd": 4,
      "note_name": "E",
      "angle": 120
    },
    {
      "channel": 0.0,
      "note": 62.0,
      "time": 25,
      "type": "note_on",
      "velocity": 70.0,
      "note_midi_value": 62.0,
      "note_velocity": 70.0,
      "note_time": 6912,
      "note_seconds": 15.709090909090909,
      "tpb": 220,
      "channel_chunk": "0.0_3.0",
      "instrument": "Acoustic Guitar (nylon)",
      "octave": 5.0,
      "note_value": 2.0,
      "note_value_nmd": 2,
      "note_name": "D",
      "angle": 60
    },
    {
      "channel": 0.0,
      "note": 60.0,
      "time": 25,
      "type": "note_on",
      "velocity": 73.0,
      "note_midi_value": 60.0,
      "note_velocity": 73.0,
      "note_time": 7168,
      "note_seconds": 16.29090909090909,
      "tpb": 220,
      "channel_chunk": "0.0_4.0",
      "instrument": "Acoustic Guitar (nylon)",
      "octave": 5.0,
      "note_value": 0.0,
      "note_value_nmd": 0,
      "note_name": "C",
      "angle": 0
    },
    {
      "channel": 0.0,
      "note": 52.0,
      "time": 0,
      "type": "note_on",
      "velocity": 72.0,
      "note_midi_value": 52.0,
      "note_velocity": 72.0,
      "note_time": 7168,
      "note_seconds": 16.29090909090909,
      "tpb": 220,
      "channel_chunk": "0.0_4.0",
      "instrument": "Acoustic Guitar (nylon)",
      "octave": 4.0,
      "note_value": 4.0,
      "note_value_nmd": 4,
      "note_name": "E",
      "angle": 120
    }
  ]
}